image_processing_ThomBrP/__init__.py
image_processing_ThomBrP/processing/__init__.py
image_processing_ThomBrP/processing/combination.py
image_processing_ThomBrP/processing/transformation.py
image_processing_ThomBrP/utils/__init__.py
image_processing_ThomBrP/utils/io.py
image_processing_ThomBrP/utils/plot.py
image_processing_ThomBrP-0.0.3.dist-info/METADATA
image_processing_ThomBrP-0.0.3.dist-info/WHEEL
image_processing_ThomBrP-0.0.3.dist-info/top_level.txt
image_processing_ThomBrP-0.0.3.dist-info/RECORD
