Metadata-Version: 2.1
Name: image_processing_ThomBrP
Version: 0.0.3
Summary: DIO Study about python packages
Home-page: https://github.com/ThomBrP/Engenharia-de-Dados-com-Python-DIO
Author: ThomBrP
Author-email: Thomasbrp@gmail.com
Requires-Python: >=3.8
Requires-Dist: matplotlib
Requires-Dist: numpy
Requires-Dist: scikit-image >=0.16.1
